<?xml version= "1.0" encoding="UTF-8" standalone="yes"?>
<Dimap_Document version="1.2">
	<Metadata_Identification>
		<METADATA_FORMAT version="3.0" profile="PNEO_SENSOR">DIMAP</METADATA_FORMAT>
		<METADATA_PROFILE>PNEO_SENSOR</METADATA_PROFILE>
		<METADATA_SUBPROFILE>RPC</METADATA_SUBPROFILE>
		<METADATA_LANGUAGE>en</METADATA_LANGUAGE>
	</Metadata_Identification>
	<Rational_Function_Model>
		<Resource_Reference>
			<RESOURCE_TITLE version="2.1">NITF</RESOURCE_TITLE>
			<RESOURCE_ID>RPC00B</RESOURCE_ID>
		</Resource_Reference>
		<Global_RFM>
			<RFM_Validity>
                <LONG_SCALE>LONG_SCALE</LONG_SCALE>
                <LONG_OFF>LONG_OFF</LONG_OFF>
                <LAT_SCALE>LAT_SCALE</LAT_SCALE>
                <LAT_OFF>LAT_OFF</LAT_OFF>
                <HEIGHT_SCALE>HEIGHT_SCALE</HEIGHT_SCALE>
                <HEIGHT_OFF>HEIGHT_OFF</HEIGHT_OFF>
				<SAMP_SCALE>7036</SAMP_SCALE>
				<SAMP_OFF>7024</SAMP_OFF>
				<LINE_SCALE>10918</LINE_SCALE>
				<LINE_OFF>10906</LINE_OFF>
			</RFM_Validity>
			<GroundtoImage_Values>
                <SAMP_NUM_COEFF_1>SAMP_NUM_COEFF_1</SAMP_NUM_COEFF_1>
                <SAMP_NUM_COEFF_2>SAMP_NUM_COEFF_2</SAMP_NUM_COEFF_2>
                <SAMP_NUM_COEFF_3>SAMP_NUM_COEFF_3</SAMP_NUM_COEFF_3>
                <SAMP_NUM_COEFF_4>SAMP_NUM_COEFF_4</SAMP_NUM_COEFF_4>
                <SAMP_NUM_COEFF_5>SAMP_NUM_COEFF_5</SAMP_NUM_COEFF_5>
                <SAMP_NUM_COEFF_6>SAMP_NUM_COEFF_6</SAMP_NUM_COEFF_6>
                <SAMP_NUM_COEFF_7>SAMP_NUM_COEFF_7</SAMP_NUM_COEFF_7>
                <SAMP_NUM_COEFF_8>SAMP_NUM_COEFF_8</SAMP_NUM_COEFF_8>
                <SAMP_NUM_COEFF_9>SAMP_NUM_COEFF_9</SAMP_NUM_COEFF_9>
                <SAMP_NUM_COEFF_10>SAMP_NUM_COEFF_10</SAMP_NUM_COEFF_10>
                <SAMP_NUM_COEFF_11>SAMP_NUM_COEFF_11</SAMP_NUM_COEFF_11>
                <SAMP_NUM_COEFF_12>SAMP_NUM_COEFF_12</SAMP_NUM_COEFF_12>
                <SAMP_NUM_COEFF_13>SAMP_NUM_COEFF_13</SAMP_NUM_COEFF_13>
                <SAMP_NUM_COEFF_14>SAMP_NUM_COEFF_14</SAMP_NUM_COEFF_14>
                <SAMP_NUM_COEFF_15>SAMP_NUM_COEFF_15</SAMP_NUM_COEFF_15>
                <SAMP_NUM_COEFF_16>SAMP_NUM_COEFF_16</SAMP_NUM_COEFF_16>
                <SAMP_NUM_COEFF_17>SAMP_NUM_COEFF_17</SAMP_NUM_COEFF_17>
                <SAMP_NUM_COEFF_18>SAMP_NUM_COEFF_18</SAMP_NUM_COEFF_18>
                <SAMP_NUM_COEFF_19>SAMP_NUM_COEFF_19</SAMP_NUM_COEFF_19>
                <SAMP_NUM_COEFF_20>SAMP_NUM_COEFF_20</SAMP_NUM_COEFF_20>
                <SAMP_DEN_COEFF_1>SAMP_DEN_COEFF_1</SAMP_DEN_COEFF_1>
                <SAMP_DEN_COEFF_2>SAMP_DEN_COEFF_2</SAMP_DEN_COEFF_2>
                <SAMP_DEN_COEFF_3>SAMP_DEN_COEFF_3</SAMP_DEN_COEFF_3>
                <SAMP_DEN_COEFF_4>SAMP_DEN_COEFF_4</SAMP_DEN_COEFF_4>
                <SAMP_DEN_COEFF_5>SAMP_DEN_COEFF_5</SAMP_DEN_COEFF_5>
                <SAMP_DEN_COEFF_6>SAMP_DEN_COEFF_6</SAMP_DEN_COEFF_6>
                <SAMP_DEN_COEFF_7>SAMP_DEN_COEFF_7</SAMP_DEN_COEFF_7>
                <SAMP_DEN_COEFF_8>SAMP_DEN_COEFF_8</SAMP_DEN_COEFF_8>
                <SAMP_DEN_COEFF_9>SAMP_DEN_COEFF_9</SAMP_DEN_COEFF_9>
                <SAMP_DEN_COEFF_10>SAMP_DEN_COEFF_10</SAMP_DEN_COEFF_10>
                <SAMP_DEN_COEFF_11>SAMP_DEN_COEFF_11</SAMP_DEN_COEFF_11>
                <SAMP_DEN_COEFF_12>SAMP_DEN_COEFF_12</SAMP_DEN_COEFF_12>
                <SAMP_DEN_COEFF_13>SAMP_DEN_COEFF_13</SAMP_DEN_COEFF_13>
                <SAMP_DEN_COEFF_14>SAMP_DEN_COEFF_14</SAMP_DEN_COEFF_14>
                <SAMP_DEN_COEFF_15>SAMP_DEN_COEFF_15</SAMP_DEN_COEFF_15>
                <SAMP_DEN_COEFF_16>SAMP_DEN_COEFF_16</SAMP_DEN_COEFF_16>
                <SAMP_DEN_COEFF_17>SAMP_DEN_COEFF_17</SAMP_DEN_COEFF_17>
                <SAMP_DEN_COEFF_18>SAMP_DEN_COEFF_18</SAMP_DEN_COEFF_18>
                <SAMP_DEN_COEFF_19>SAMP_DEN_COEFF_19</SAMP_DEN_COEFF_19>
                <SAMP_DEN_COEFF_20>SAMP_DEN_COEFF_20</SAMP_DEN_COEFF_20>
                <LINE_NUM_COEFF_1>LINE_NUM_COEFF_1</LINE_NUM_COEFF_1>
                <LINE_NUM_COEFF_2>LINE_NUM_COEFF_2</LINE_NUM_COEFF_2>
                <LINE_NUM_COEFF_3>LINE_NUM_COEFF_3</LINE_NUM_COEFF_3>
                <LINE_NUM_COEFF_4>LINE_NUM_COEFF_4</LINE_NUM_COEFF_4>
                <LINE_NUM_COEFF_5>LINE_NUM_COEFF_5</LINE_NUM_COEFF_5>
                <LINE_NUM_COEFF_6>LINE_NUM_COEFF_6</LINE_NUM_COEFF_6>
                <LINE_NUM_COEFF_7>LINE_NUM_COEFF_7</LINE_NUM_COEFF_7>
                <LINE_NUM_COEFF_8>LINE_NUM_COEFF_8</LINE_NUM_COEFF_8>
                <LINE_NUM_COEFF_9>LINE_NUM_COEFF_9</LINE_NUM_COEFF_9>
                <LINE_NUM_COEFF_10>LINE_NUM_COEFF_10</LINE_NUM_COEFF_10>
                <LINE_NUM_COEFF_11>LINE_NUM_COEFF_11</LINE_NUM_COEFF_11>
                <LINE_NUM_COEFF_12>LINE_NUM_COEFF_12</LINE_NUM_COEFF_12>
                <LINE_NUM_COEFF_13>LINE_NUM_COEFF_13</LINE_NUM_COEFF_13>
                <LINE_NUM_COEFF_14>LINE_NUM_COEFF_14</LINE_NUM_COEFF_14>
                <LINE_NUM_COEFF_15>LINE_NUM_COEFF_15</LINE_NUM_COEFF_15>
                <LINE_NUM_COEFF_16>LINE_NUM_COEFF_16</LINE_NUM_COEFF_16>
                <LINE_NUM_COEFF_17>LINE_NUM_COEFF_17</LINE_NUM_COEFF_17>
                <LINE_NUM_COEFF_18>LINE_NUM_COEFF_18</LINE_NUM_COEFF_18>
                <LINE_NUM_COEFF_19>LINE_NUM_COEFF_19</LINE_NUM_COEFF_19>
                <LINE_NUM_COEFF_20>LINE_NUM_COEFF_20</LINE_NUM_COEFF_20>
                <LINE_DEN_COEFF_1>LINE_DEN_COEFF_1</LINE_DEN_COEFF_1>
                <LINE_DEN_COEFF_2>LINE_DEN_COEFF_2</LINE_DEN_COEFF_2>
                <LINE_DEN_COEFF_3>LINE_DEN_COEFF_3</LINE_DEN_COEFF_3>
                <LINE_DEN_COEFF_4>LINE_DEN_COEFF_4</LINE_DEN_COEFF_4>
                <LINE_DEN_COEFF_5>LINE_DEN_COEFF_5</LINE_DEN_COEFF_5>
                <LINE_DEN_COEFF_6>LINE_DEN_COEFF_6</LINE_DEN_COEFF_6>
                <LINE_DEN_COEFF_7>LINE_DEN_COEFF_7</LINE_DEN_COEFF_7>
                <LINE_DEN_COEFF_8>LINE_DEN_COEFF_8</LINE_DEN_COEFF_8>
                <LINE_DEN_COEFF_9>LINE_DEN_COEFF_9</LINE_DEN_COEFF_9>
                <LINE_DEN_COEFF_10>LINE_DEN_COEFF_10</LINE_DEN_COEFF_10>
                <LINE_DEN_COEFF_11>LINE_DEN_COEFF_11</LINE_DEN_COEFF_11>
                <LINE_DEN_COEFF_12>LINE_DEN_COEFF_12</LINE_DEN_COEFF_12>
                <LINE_DEN_COEFF_13>LINE_DEN_COEFF_13</LINE_DEN_COEFF_13>
                <LINE_DEN_COEFF_14>LINE_DEN_COEFF_14</LINE_DEN_COEFF_14>
                <LINE_DEN_COEFF_15>LINE_DEN_COEFF_15</LINE_DEN_COEFF_15>
                <LINE_DEN_COEFF_16>LINE_DEN_COEFF_16</LINE_DEN_COEFF_16>
                <LINE_DEN_COEFF_17>LINE_DEN_COEFF_17</LINE_DEN_COEFF_17>
                <LINE_DEN_COEFF_18>LINE_DEN_COEFF_18</LINE_DEN_COEFF_18>
                <LINE_DEN_COEFF_19>LINE_DEN_COEFF_19</LINE_DEN_COEFF_19>
                <LINE_DEN_COEFF_20>LINE_DEN_COEFF_20</LINE_DEN_COEFF_20>
                <ERR_BIAS_X>ERR_BIAS_X</ERR_BIAS_X>
                <ERR_BIAS_Y>ERR_BIAS_Y</ERR_BIAS_Y>
			</GroundtoImage_Values>
		</Global_RFM>
	</Rational_Function_Model>
</Dimap_Document>
